netlify_site_clone/__init__.py
netlify_site_clone/_cli.py
netlify_site_clone-0.5.0.dist-info/LICENSE
netlify_site_clone-0.5.0.dist-info/METADATA
netlify_site_clone-0.5.0.dist-info/WHEEL
netlify_site_clone-0.5.0.dist-info/entry_points.txt
netlify_site_clone-0.5.0.dist-info/top_level.txt
netlify_site_clone-0.5.0.dist-info/RECORD
