Metadata-Version: 2.1
Name: netlify-site-clone
Version: 0.5.0
Summary: tool for cloning Netlify sites
Home-page: https://github.com/kshpytsya/netlify-site-clone
Author: Kyrylo Shpytsya
Author-email: kshpitsa@gmail.com
License: MIT
Platform: UNKNOWN
Classifier: Development Status :: 4 - Beta
Classifier: Intended Audience :: Developers
Classifier: Intended Audience :: Information Technology
Classifier: Intended Audience :: System Administrators
Classifier: License :: OSI Approved :: MIT License
Classifier: Operating System :: POSIX
Classifier: Programming Language :: Python :: 3.6
Classifier: Programming Language :: Python :: 3.7
Classifier: Programming Language :: Python :: 3.8
Classifier: Programming Language :: Python :: 3.9
Classifier: Topic :: Internet :: WWW/HTTP :: HTTP Servers
Classifier: Topic :: System :: Systems Administration
Requires-Python: >=3.6, <3.10
Requires-Dist: click (<8,>=7.1.2)
Requires-Dist: click-log (<1,>=0.3.2)
Requires-Dist: dnspython (<2,>=1.16.0)
Requires-Dist: requests (<3,>=2.24.0)
